Workbook

Sheet 📊 Dashboard
B2: ✦ MAGNIFYSCENTS · Sales Performance Dashboard ✦
B3: 2026 · All Channels · ⚡ Live — add rows to Raw Data and this dashboard updates instantly
B6: 💰 Total Revenue | D6: 🛒 Total Orders | F6: 📦 Units Sold | H6: 💳 Avg Order Value
B7: =TEXT('🔢 Calc'!B21,"₹#,##0") -> ₹420,732 | D7: ='🔢 Calc'!B22 -> 200 | F7: ='🔢 Calc'!B23 -> 588 | H7: =TEXT('🔢 Calc'!B24,"₹#,##0") -> ₹2,104
B11: 📅 Monthly Revenue Summary · auto-updates when new rows are added
B12: Month | C12: Revenue (INR) | D12: Orders | E12: Units | F12: Avg Order (INR) | G12: MoM Growth
B13: Jan 2026 | C13: =IFERROR(TEXT('🔢 Calc'!B4,"₹#,##0"),"—") -> ₹137,124 | D13: =IFERROR('🔢 Calc'!C4,"—") -> 67 | E13: =IFERROR('🔢 Calc'!D4,"—") -> 190 | F13: =IFERROR(TEXT('🔢 Calc'!B4/'🔢 Calc'!C4,"₹#,##0"),"—") -> ₹2,047 | G13: —
B14: Feb 2026 | C14: =IFERROR(TEXT('🔢 Calc'!B5,"₹#,##0"),"—") -> ₹133,380 | D14: =IFERROR('🔢 Calc'!C5,"—") -> 61 | E14: =IFERROR('🔢 Calc'!D5,"—") -> 184 | F14: =IFERROR(TEXT('🔢 Calc'!B5/'🔢 Calc'!C5,"₹#,##0"),"—") -> ₹2,187 | G14: =IFERROR(IF(AND(ISNUMBER('🔢 Calc'!B5),ISNUMBER('🔢 Calc'!B4)),TEXT(('🔢 Calc'!B5-'🔢 Calc'!B4)/'🔢 Calc'!B4,"+0.0%;-0.0%"),"—"),"—") -> -2.7%
B15: Mar 2026 | C15: =IFERROR(TEXT('🔢 Calc'!B6,"₹#,##0"),"—") -> ₹145,028 | D15: =IFERROR('🔢 Calc'!C6,"—") -> 71 | E15: =IFERROR('🔢 Calc'!D6,"—") -> 209 | F15: =IFERROR(TEXT('🔢 Calc'!B6/'🔢 Calc'!C6,"₹#,##0"),"—") -> ₹2,043 | G15: =IFERROR(IF(AND(ISNUMBER('🔢 Calc'!B6),ISNUMBER('🔢 Calc'!B5)),TEXT(('🔢 Calc'!B6-'🔢 Calc'!B5)/'🔢 Calc'!B5,"+0.0%;-0.0%"),"—"),"—") -> +8.7%
B16: Apr 2026 | C16: =IFERROR(TEXT('🔢 Calc'!B7,"₹#,##0"),"—") -> ₹5,200 | D16: =IFERROR('🔢 Calc'!C7,"—") -> 1 | E16: =IFERROR('🔢 Calc'!D7,"—") -> 5 | F16: =IFERROR(TEXT('🔢 Calc'!B7/'🔢 Calc'!C7,"₹#,##0"),"—") -> ₹5,200 | G16: =IFERROR(IF(AND(ISNUMBER('🔢 Calc'!B7),ISNUMBER('🔢 Calc'!B6)),TEXT(('🔢 Calc'!B7-'🔢 Calc'!B6)/'🔢 Calc'!B6,"+0.0%;-0.0%"),"—"),"—") -> -96.4%
B17: May 2026 | C17: =IFERROR(TEXT('🔢 Calc'!B8,"₹#,##0"),"—") -> ₹0 | D17: =IFERROR('🔢 Calc'!C8,"—") -> 0 | E17: =IFERROR('🔢 Calc'!D8,"—") -> 0 | F17: =IFERROR(TEXT('🔢 Calc'!B8/'🔢 Calc'!C8,"₹#,##0"),"—") -> — | G17: =IFERROR(IF(AND(ISNUMBER('🔢 Calc'!B8),ISNUMBER('🔢 Calc'!B7)),TEXT(('🔢 Calc'!B8-'🔢 Calc'!B7)/'🔢 Calc'!B7,"+0.0%;-0.0%"),"—"),"—") -> -100.0%
B18: Jun 2026 | C18: =IFERROR(TEXT('🔢 Calc'!B9,"₹#,##0"),"—") -> ₹0 | D18: =IFERROR('🔢 Calc'!C9,"—") -> 0 | E18: =IFERROR('🔢 Calc'!D9,"—") -> 0 | F18: =IFERROR(TEXT('🔢 Calc'!B9/'🔢 Calc'!C9,"₹#,##0"),"—") -> — | G18: =IFERROR(IF(AND(ISNUMBER('🔢 Calc'!B9),ISNUMBER('🔢 Calc'!B8)),TEXT(('🔢 Calc'!B9-'🔢 Calc'!B8)/'🔢 Calc'!B8,"+0.0%;-0.0%"),"—"),"—") -> —
B19: Jul 2026 | C19: =IFERROR(TEXT('🔢 Calc'!B10,"₹#,##0"),"—") -> ₹0 | D19: =IFERROR('🔢 Calc'!C10,"—") -> 0 | E19: =IFERROR('🔢 Calc'!D10,"—") -> 0 | F19: =IFERROR(TEXT('🔢 Calc'!B10/'🔢 Calc'!C10,"₹#,##0"),"—") -> — | G19: =IFERROR(IF(AND(ISNUMBER('🔢 Calc'!B10),ISNUMBER('🔢 Calc'!B9)),TEXT(('🔢 Calc'!B10-'🔢 Calc'!B9)/'🔢 Calc'!B9,"+0.0%;-0.0%"),"—"),"—") -> —
B20: Aug 2026 | C20: =IFERROR(TEXT('🔢 Calc'!B11,"₹#,##0"),"—") -> ₹0 | D20: =IFERROR('🔢 Calc'!C11,"—") -> 0 | E20: =IFERROR('🔢 Calc'!D11,"—") -> 0 | F20: =IFERROR(TEXT('🔢 Calc'!B11/'🔢 Calc'!C11,"₹#,##0"),"—") -> — | G20: =IFERROR(IF(AND(ISNUMBER('🔢 Calc'!B11),ISNUMBER('🔢 Calc'!B10)),TEXT(('🔢 Calc'!B11-'🔢 Calc'!B10)/'🔢 Calc'!B10,"+0.0%;-0.0%"),"—"),"—") -> —
B21: Sep 2026 | C21: =IFERROR(TEXT('🔢 Calc'!B12,"₹#,##0"),"—") -> ₹0 | D21: =IFERROR('🔢 Calc'!C12,"—") -> 0 | E21: =IFERROR('🔢 Calc'!D12,"—") -> 0 | F21: =IFERROR(TEXT('🔢 Calc'!B12/'🔢 Calc'!C12,"₹#,##0"),"—") -> — | G21: =IFERROR(IF(AND(ISNUMBER('🔢 Calc'!B12),ISNUMBER('🔢 Calc'!B11)),TEXT(('🔢 Calc'!B12-'🔢 Calc'!B11)/'🔢 Calc'!B11,"+0.0%;-0.0%"),"—"),"—") -> —
B22: Oct 2026 | C22: =IFERROR(TEXT('🔢 Calc'!B13,"₹#,##0"),"—") -> ₹0 | D22: =IFERROR('🔢 Calc'!C13,"—") -> 0 | E22: =IFERROR('🔢 Calc'!D13,"—") -> 0 | F22: =IFERROR(TEXT('🔢 Calc'!B13/'🔢 Calc'!C13,"₹#,##0"),"—") -> — | G22: =IFERROR(IF(AND(ISNUMBER('🔢 Calc'!B13),ISNUMBER('🔢 Calc'!B12)),TEXT(('🔢 Calc'!B13-'🔢 Calc'!B12)/'🔢 Calc'!B12,"+0.0%;-0.0%"),"—"),"—") -> —
B23: Nov 2026 | C23: =IFERROR(TEXT('🔢 Calc'!B14,"₹#,##0"),"—") -> ₹0 | D23: =IFERROR('🔢 Calc'!C14,"—") -> 0 | E23: =IFERROR('🔢 Calc'!D14,"—") -> 0 | F23: =IFERROR(TEXT('🔢 Calc'!B14/'🔢 Calc'!C14,"₹#,##0"),"—") -> — | G23: =IFERROR(IF(AND(ISNUMBER('🔢 Calc'!B14),ISNUMBER('🔢 Calc'!B13)),TEXT(('🔢 Calc'!B14-'🔢 Calc'!B13)/'🔢 Calc'!B13,"+0.0%;-0.0%"),"—"),"—") -> —
B24: Dec 2026 | C24: =IFERROR(TEXT('🔢 Calc'!B15,"₹#,##0"),"—") -> ₹0 | D24: =IFERROR('🔢 Calc'!C15,"—") -> 0 | E24: =IFERROR('🔢 Calc'!D15,"—") -> 0 | F24: =IFERROR(TEXT('🔢 Calc'!B15/'🔢 Calc'!C15,"₹#,##0"),"—") -> — | G24: =IFERROR(IF(AND(ISNUMBER('🔢 Calc'!B15),ISNUMBER('🔢 Calc'!B14)),TEXT(('🔢 Calc'!B15-'🔢 Calc'!B14)/'🔢 Calc'!B14,"+0.0%;-0.0%"),"—"),"—") -> —
B27: 🏆 Product Performance · auto-updates | F27: 📱 Sales Channel Breakdown · auto-updates
B28: Product | C28: Revenue (INR) | D28: Units | E28: Orders | F28: Channel | G28: Revenue (INR) | H28: Orders | I28: % Share
B29: 🥇 Amber Gold | C29: =TEXT('🔢 Calc'!G4,"₹#,##0") -> ₹96,720 | D29: ='🔢 Calc'!H4 -> 93 | E29: ='🔢 Calc'!I4 -> 29 | F29: In-person | G29: =TEXT('🔢 Calc'!L4,"₹#,##0") -> ₹154,388 | H29: ='🔢 Calc'!M4 -> 75 | I29: =IFERROR(TEXT('🔢 Calc'!L4/(SUM('🔢 Calc'!L4:L6)),"0.0%"),"—") -> 36.7%
B30: 🥈 Citrus Fresh | C30: =TEXT('🔢 Calc'!G5,"₹#,##0") -> ₹88,920 | D30: ='🔢 Calc'!H5 -> 95 | E30: ='🔢 Calc'!I5 -> 38 | F30: Instagram | G30: =TEXT('🔢 Calc'!L5,"₹#,##0") -> ₹141,752 | H30: ='🔢 Calc'!M5 -> 64 | I30: =IFERROR(TEXT('🔢 Calc'!L5/(SUM('🔢 Calc'!L4:L6)),"0.0%"),"—") -> 33.7%
B31: 🥉 Rose Elixir | C31: =TEXT('🔢 Calc'!G8,"₹#,##0") -> ₹88,140 | D31: ='🔢 Calc'!H8 -> 113 | E31: ='🔢 Calc'!I8 -> 37 | F31: WhatsApp | G31: =TEXT('🔢 Calc'!L6,"₹#,##0") -> ₹124,592 | H31: ='🔢 Calc'!M6 -> 61 | I31: =IFERROR(TEXT('🔢 Calc'!L6/(SUM('🔢 Calc'!L4:L6)),"0.0%"),"—") -> 29.6%
B32: 4th Vanilla Bliss | C32: =TEXT('🔢 Calc'!G9,"₹#,##0") -> ₹56,680 | D32: ='🔢 Calc'!H9 -> 109 | E32: ='🔢 Calc'!I9 -> 35
B33: 5th Midnight Musk | C33: =TEXT('🔢 Calc'!G6,"₹#,##0") -> ₹48,672 | D33: ='🔢 Calc'!H6 -> 78 | E33: ='🔢 Calc'!I6 -> 29
B34: 6th Oud Royale | C34: =TEXT('🔢 Calc'!G7,"₹#,##0") -> ₹41,600 | D34: ='🔢 Calc'!H7 -> 100 | E34: ='🔢 Calc'!I7 -> 32
B36: 💳 Payment Method · auto-updates | F36: 🎯 Category Breakdown · auto-updates
B37: Payment | C37: Revenue (INR) | D37: Orders | E37: % Share | F37: Category | G37: Revenue (INR) | H37: Units | I37: % Share
B38: Cash | C38: =TEXT('🔢 Calc'!P4,"₹#,##0") -> ₹111,748 | D38: ='🔢 Calc'!Q4 -> 60 | E38: =IFERROR(TEXT('🔢 Calc'!P4/(SUM('🔢 Calc'!P4:P6)),"0.0%"),"—") -> 26.6% | F38: Men | G38: =TEXT('🔢 Calc'!T4,"₹#,##0") -> ₹145,392 | H38: ='🔢 Calc'!U4 -> 171 | I38: =IFERROR(TEXT('🔢 Calc'!T4/(SUM('🔢 Calc'!T4:T6)),"0.0%"),"—") -> 34.6%
B39: POS | C39: =TEXT('🔢 Calc'!P5,"₹#,##0") -> ₹165,620 | D39: ='🔢 Calc'!Q5 -> 71 | E39: =IFERROR(TEXT('🔢 Calc'!P5/(SUM('🔢 Calc'!P4:P6)),"0.0%"),"—") -> 39.4% | F39: Unisex | G39: =TEXT('🔢 Calc'!T5,"₹#,##0") -> ₹130,520 | H39: ='🔢 Calc'!U5 -> 195 | I39: =IFERROR(TEXT('🔢 Calc'!T5/(SUM('🔢 Calc'!T4:T6)),"0.0%"),"—") -> 31.0%
B40: Transfer | C40: =TEXT('🔢 Calc'!P6,"₹#,##0") -> ₹143,364 | D40: ='🔢 Calc'!Q6 -> 69 | E40: =IFERROR(TEXT('🔢 Calc'!P6/(SUM('🔢 Calc'!P4:P6)),"0.0%"),"—") -> 34.1% | F40: Women | G40: =TEXT('🔢 Calc'!T6,"₹#,##0") -> ₹144,820 | H40: ='🔢 Calc'!U6 -> 222 | I40: =IFERROR(TEXT('🔢 Calc'!T6/(SUM('🔢 Calc'!T4:T6)),"0.0%"),"—") -> 34.4%
B42: ✦ Just add rows to the Raw Data sheet → All KPIs, tables and charts refresh instantly · MagnifyScents 2026 ✦

Sheet 📈 Charts
A1: ✦ MagnifyScents · Visual Analytics · All 8 charts update when new sales are added ✦
A3: 📈 Monthly Revenue Trend (INR) · auto-updates | H3: 📊 Monthly Orders Count · auto-updates
A21: 🏆 Revenue by Product (INR) · auto-updates | H21: 📦 Units Sold by Product · auto-updates
A39: 📱 Revenue Share by Sales Channel · auto-updates | H39: 💳 Revenue Share by Payment Method · auto-updates
A57: 🎯 Revenue by Category (INR) · auto-updates | H57: 📦 Units Sold by Category · auto-updates
A76: ✦ All 8 charts refresh automatically · Add rows to Raw Data sheet to see new months appear · MagnifyScents ✦

Sheet 📋 Raw Data
A1: Order ID | B1: Date | C1: Product Name | D1: Category | E1: Quantity | F1: Sales Channel | G1: Payment Method | H1: Unit Price (INR) | I1: Total Revenue (INR)
A2: ORD001 | B2: 2026-02-07 | C2: Citrus Fresh | D2: Unisex | E2: 2 | F2: WhatsApp | G2: Transfer | H2: 936 | I2: 1872
A3: ORD002 | B3: 2026-03-26 | C3: Midnight Musk | D3: Men | E3: 2 | F3: WhatsApp | G3: Transfer | H3: 624 | I3: 1248
A4: ORD003 | B4: 2026-02-12 | C4: Midnight Musk | D4: Men | E4: 3 | F4: Instagram | G4: POS | H4: 624 | I4: 1872
A5: ORD004 | B5: 2026-01-13 | C5: Citrus Fresh | D5: Unisex | E5: 2 | F5: In-person | G5: Transfer | H5: 936 | I5: 1872
A6: ORD005 | B6: 2026-03-24 | C6: Citrus Fresh | D6: Unisex | E6: 1 | F6: Instagram | G6: POS | H6: 936 | I6: 936
A7: ORD006 | B7: 2026-02-12 | C7: Oud Royale | D7: Unisex | E7: 1 | F7: Instagram | G7: POS | H7: 416 | I7: 416
A8: ORD007 | B8: 2026-03-26 | C8: Citrus Fresh | D8: Unisex | E8: 5 | F8: Instagram | G8: POS | H8: 936 | I8: 4680
A9: ORD008 | B9: 2026-02-10 | C9: Rose Elixir | D9: Women | E9: 5 | F9: Instagram | G9: Transfer | H9: 780 | I9: 3900
A10: ORD009 | B10: 2026-01-18 | C10: Vanilla Bliss | D10: Women | E10: 3 | F10: Instagram | G10: POS | H10: 520 | I10: 1560
A11: ORD010 | B11: 2026-01-17 | C11: Citrus Fresh | D11: Unisex | E11: 2 | F11: Instagram | G11: Transfer | H11: 936 | I11: 1872
A12: ORD011 | B12: 2026-03-13 | C12: Amber Gold | D12: Men | E12: 2 | F12: Instagram | G12: Cash | H12: 1040 | I12: 2080
A13: ORD012 | B13: 2026-03-26 | C13: Amber Gold | D13: Men | E13: 4 | F13: In-person | G13: POS | H13: 1040 | I13: 4160
... A201: ORD200 | B201: 2026-01-19 | C201: Rose Elixir | D201: Women | E201: 4 | F201: WhatsApp | G201: POS | H201: 780 | I201: 3120
A203: ⬇ TO ADD FUTURE SALES: Type new rows directly below the last row above — the Table expands automatically and ALL charts & the Dashboard update instantly

Sheet 💡 Insights
A1: 💡 MagnifyScents · Key Insights & Recommendations
A3: 🏆 TOP PERFORMER
A4: 'Amber Gold' leads all products by revenue. Keep it well-stocked and promote it across every channel.
A6: 📱 BEST CHANNEL
A7: 'In-person' drives the most revenue. Allocate more marketing spend and exclusive offers here.
A9: 📅 PEAK MONTH
A10: Mar 2026 was your strongest month. Identify what drove it — promotions, season, events — and replicate it.
A12: 📉 QUIET PERIOD
A13: Apr 2026 was your slowest month. Plan targeted campaigns or bundle deals during similar periods ahead.
A15: 💳 PAYMENTS
A16: Cash, POS, and Bank Transfer are all active. Always keep all 3 available — restricting options reduces conversions.
A18: 📦 STOCK ALERT
... A25: Add new order rows to the Raw Data sheet. The Excel Table expands automatically — every chart, KPI, and table refreshes instantly. No manual work needed.

Sheet 🔢 Calc
A1: 🔢 Auto-Calc — All formulas reference the SalesData Table. Add rows to Raw Data → everything updates automatically.
A3: Month | B3: Revenue (INR) | C3: Orders | D3: Units | F3: Product | G3: Revenue (INR) | H3: Units | I3: Orders | K3: Channel | L3: Revenue (INR) | M3: Orders | O3: Payment | P3: Revenue (INR) | Q3: Orders | S3: Category | T3: Revenue (INR) | U3: Units
A4: Jan 2026 | B4: =IFERROR(IF(SUMPRODUCT((TEXT(SalesData[Date],"mmm yyyy")=A4)*SalesData[Total Revenue (INR)])=0,0,SUMPRODUCT((TEXT(SalesData[Date],"mmm yyyy")=A4)*SalesData[Total Revenue (INR)])),0) -> 137124 | C4: =IFERROR(IF(SUMPRODUCT((TEXT(SalesData[Date],"mmm yyyy")=A4)*(SalesData[Order ID]<>""))=0,0,SUMPRODUCT((TEXT(SalesData[Date],"mmm yyyy")=A4)*(SalesData[Order ID]<>""))),0) -> 67 | D4: =IFERROR(IF(SUMPRODUCT((TEXT(SalesData[Date],"mmm yyyy")=A4)*SalesData[Quantity])=0,0,SUMPRODUCT((TEXT(SalesData[Date],"mmm yyyy")=A4)*SalesData[Quantity])),0) -> 190 | F4: Amber Gold | G4: =SUMIF(SalesData[Product Name],F4,SalesData[Total Revenue (INR)]) -> 96720 | H4: =SUMIF(SalesData[Product Name],F4,SalesData[Quantity]) -> 93 | I4: =COUNTIF(SalesData[Product Name],F4) -> 29 | K4: In-person | L4: =SUMIF(SalesData[Sales Channel],K4,SalesData[Total Revenue (INR)]) -> 154388 | M4: =COUNTIF(SalesData[Sales Channel],K4) -> 75 | O4: Cash | P4: =SUMIF(SalesData[Payment Method],O4,SalesData[Total Revenue (INR)]) -> 111748 | Q4: =COUNTIF(SalesData[Payment Method],O4) -> 60 | S4: Men | T4: =SUMIF(SalesData[Category],S4,SalesData[Total Revenue (INR)]) -> 145392 | U4: =SUMIF(SalesData[Category],S4,SalesData[Quantity]) -> 171
A5: Feb 2026 | B5: =IFERROR(IF(SUMPRODUCT((TEXT(SalesData[Date],"mmm yyyy")=A5)*SalesData[Total Revenue (INR)])=0,0,SUMPRODUCT((TEXT(SalesData[Date],"mmm yyyy")=A5)*SalesData[Total Revenue (INR)])),0) -> 133380 | C5: =IFERROR(IF(SUMPRODUCT((TEXT(SalesData[Date],"mmm yyyy")=A5)*(SalesData[Order ID]<>""))=0,0,SUMPRODUCT((TEXT(SalesData[Date],"mmm yyyy")=A5)*(SalesData[Order ID]<>""))),0) -> 61 | D5: =IFERROR(IF(SUMPRODUCT((TEXT(SalesData[Date],"mmm yyyy")=A5)*SalesData[Quantity])=0,0,SUMPRODUCT((TEXT(SalesData[Date],"mmm yyyy")=A5)*SalesData[Quantity])),0) -> 184 | F5: Citrus Fresh | G5: =SUMIF(SalesData[Product Name],F5,SalesData[Total Revenue (INR)]) -> 88920 | H5: =SUMIF(SalesData[Product Name],F5,SalesData[Quantity]) -> 95 | I5: =COUNTIF(SalesData[Product Name],F5) -> 38 | K5: Instagram | L5: =SUMIF(SalesData[Sales Channel],K5,SalesData[Total Revenue (INR)]) -> 141752 | M5: =COUNTIF(SalesData[Sales Channel],K5) -> 64 | O5: POS | P5: =SUMIF(SalesData[Payment Method],O5,SalesData[Total Revenue (INR)]) -> 165620 | Q5: =COUNTIF(SalesData[Payment Method],O5) -> 71 | S5: Unisex | T5: =SUMIF(SalesData[Category],S5,SalesData[Total Revenue (INR)]) -> 130520 | U5: =SUMIF(SalesData[Category],S5,SalesData[Quantity]) -> 195
A6: Mar 2026 | B6: =IFERROR(IF(SUMPRODUCT((TEXT(SalesData[Date],"mmm yyyy")=A6)*SalesData[Total Revenue (INR)])=0,0,SUMPRODUCT((TEXT(SalesData[Date],"mmm yyyy")=A6)*SalesData[Total Revenue (INR)])),0) -> 145028 | C6: =IFERROR(IF(SUMPRODUCT((TEXT(SalesData[Date],"mmm yyyy")=A6)*(SalesData[Order ID]<>""))=0,0,SUMPRODUCT((TEXT(SalesData[Date],"mmm yyyy")=A6)*(SalesData[Order ID]<>""))),0) -> 71 | D6: =IFERROR(IF(SUMPRODUCT((TEXT(SalesData[Date],"mmm yyyy")=A6)*SalesData[Quantity])=0,0,SUMPRODUCT((TEXT(SalesData[Date],"mmm yyyy")=A6)*SalesData[Quantity])),0) -> 209 | F6: Midnight Musk | G6: =SUMIF(SalesData[Product Name],F6,SalesData[Total Revenue (INR)]) -> 48672 | H6: =SUMIF(SalesData[Product Name],F6,SalesData[Quantity]) -> 78 | I6: =COUNTIF(SalesData[Product Name],F6) -> 29 | K6: WhatsApp | L6: =SUMIF(SalesData[Sales Channel],K6,SalesData[Total Revenue (INR)]) -> 124592 | M6: =COUNTIF(SalesData[Sales Channel],K6) -> 61 | O6: Transfer | P6: =SUMIF(SalesData[Payment Method],O6,SalesData[Total Revenue (INR)]) -> 143364 | Q6: =COUNTIF(SalesData[Payment Method],O6) -> 69 | S6: Women | T6: =SUMIF(SalesData[Category],S6,SalesData[Total Revenue (INR)]) -> 144820 | U6: =SUMIF(SalesData[Category],S6,SalesData[Quantity]) -> 222
A7: Apr 2026 | B7: =IFERROR(IF(SUMPRODUCT((TEXT(SalesData[Date],"mmm yyyy")=A7)*SalesData[Total Revenue (INR)])=0,0,SUMPRODUCT((TEXT(SalesData[Date],"mmm yyyy")=A7)*SalesData[Total Revenue (INR)])),0) -> 5200 | C7: =IFERROR(IF(SUMPRODUCT((TEXT(SalesData[Date],"mmm yyyy")=A7)*(SalesData[Order ID]<>""))=0,0,SUMPRODUCT((TEXT(SalesData[Date],"mmm yyyy")=A7)*(SalesData[Order ID]<>""))),0) -> 1 | D7: =IFERROR(IF(SUMPRODUCT((TEXT(SalesData[Date],"mmm yyyy")=A7)*SalesData[Quantity])=0,0,SUMPRODUCT((TEXT(SalesData[Date],"mmm yyyy")=A7)*SalesData[Quantity])),0) -> 5 | F7: Oud Royale | G7: =SUMIF(SalesData[Product Name],F7,SalesData[Total Revenue (INR)]) -> 41600 | H7: =SUMIF(SalesData[Product Name],F7,SalesData[Quantity]) -> 100 | I7: =COUNTIF(SalesData[Product Name],F7) -> 32
A8: May 2026 | B8: =IFERROR(IF(SUMPRODUCT((TEXT(SalesData[Date],"mmm yyyy")=A8)*SalesData[Total Revenue (INR)])=0,0,SUMPRODUCT((TEXT(SalesData[Date],"mmm yyyy")=A8)*SalesData[Total Revenue (INR)])),0) -> 0 | C8: =IFERROR(IF(SUMPRODUCT((TEXT(SalesData[Date],"mmm yyyy")=A8)*(SalesData[Order ID]<>""))=0,0,SUMPRODUCT((TEXT(SalesData[Date],"mmm yyyy")=A8)*(SalesData[Order ID]<>""))),0) -> 0 | D8: =IFERROR(IF(SUMPRODUCT((TEXT(SalesData[Date],"mmm yyyy")=A8)*SalesData[Quantity])=0,0,SUMPRODUCT((TEXT(SalesData[Date],"mmm yyyy")=A8)*SalesData[Quantity])),0) -> 0 | F8: Rose Elixir | G8: =SUMIF(SalesData[Product Name],F8,SalesData[Total Revenue (INR)]) -> 88140 | H8: =SUMIF(SalesData[Product Name],F8,SalesData[Quantity]) -> 113 | I8: =COUNTIF(SalesData[Product Name],F8) -> 37
A9: Jun 2026 | B9: =IFERROR(IF(SUMPRODUCT((TEXT(SalesData[Date],"mmm yyyy")=A9)*SalesData[Total Revenue (INR)])=0,0,SUMPRODUCT((TEXT(SalesData[Date],"mmm yyyy")=A9)*SalesData[Total Revenue (INR)])),0) -> 0 | C9: =IFERROR(IF(SUMPRODUCT((TEXT(SalesData[Date],"mmm yyyy")=A9)*(SalesData[Order ID]<>""))=0,0,SUMPRODUCT((TEXT(SalesData[Date],"mmm yyyy")=A9)*(SalesData[Order ID]<>""))),0) -> 0 | D9: =IFERROR(IF(SUMPRODUCT((TEXT(SalesData[Date],"mmm yyyy")=A9)*SalesData[Quantity])=0,0,SUMPRODUCT((TEXT(SalesData[Date],"mmm yyyy")=A9)*SalesData[Quantity])),0) -> 0 | F9: Vanilla Bliss | G9: =SUMIF(SalesData[Product Name],F9,SalesData[Total Revenue (INR)]) -> 56680 | H9: =SUMIF(SalesData[Product Name],F9,SalesData[Quantity]) -> 109 | I9: =COUNTIF(SalesData[Product Name],F9) -> 35
A10: Jul 2026 | B10: =IFERROR(IF(SUMPRODUCT((TEXT(SalesData[Date],"mmm yyyy")=A10)*SalesData[Total Revenue (INR)])=0,0,SUMPRODUCT((TEXT(SalesData[Date],"mmm yyyy")=A10)*SalesData[Total Revenue (INR)])),0) -> 0 | C10: =IFERROR(IF(SUMPRODUCT((TEXT(SalesData[Date],"mmm yyyy")=A10)*(SalesData[Order ID]<>""))=0,0,SUMPRODUCT((TEXT(SalesData[Date],"mmm yyyy")=A10)*(SalesData[Order ID]<>""))),0) -> 0 | D10: =IFERROR(IF(SUMPRODUCT((TEXT(SalesData[Date],"mmm yyyy")=A10)*SalesData[Quantity])=0,0,SUMPRODUCT((TEXT(SalesData[Date],"mmm yyyy")=A10)*SalesData[Quantity])),0) -> 0
A11: Aug 2026 | B11: =IFERROR(IF(SUMPRODUCT((TEXT(SalesData[Date],"mmm yyyy")=A11)*SalesData[Total Revenue (INR)])=0,0,SUMPRODUCT((TEXT(SalesData[Date],"mmm yyyy")=A11)*SalesData[Total Revenue (INR)])),0) -> 0 | C11: =IFERROR(IF(SUMPRODUCT((TEXT(SalesData[Date],"mmm yyyy")=A11)*(SalesData[Order ID]<>""))=0,0,SUMPRODUCT((TEXT(SalesData[Date],"mmm yyyy")=A11)*(SalesData[Order ID]<>""))),0) -> 0 | D11: =IFERROR(IF(SUMPRODUCT((TEXT(SalesData[Date],"mmm yyyy")=A11)*SalesData[Quantity])=0,0,SUMPRODUCT((TEXT(SalesData[Date],"mmm yyyy")=A11)*SalesData[Quantity])),0) -> 0
A12: Sep 2026 | B12: =IFERROR(IF(SUMPRODUCT((TEXT(SalesData[Date],"mmm yyyy")=A12)*SalesData[Total Revenue (INR)])=0,0,SUMPRODUCT((TEXT(SalesData[Date],"mmm yyyy")=A12)*SalesData[Total Revenue (INR)])),0) -> 0 | C12: =IFERROR(IF(SUMPRODUCT((TEXT(SalesData[Date],"mmm yyyy")=A12)*(SalesData[Order ID]<>""))=0,0,SUMPRODUCT((TEXT(SalesData[Date],"mmm yyyy")=A12)*(SalesData[Order ID]<>""))),0) -> 0 | D12: =IFERROR(IF(SUMPRODUCT((TEXT(SalesData[Date],"mmm yyyy")=A12)*SalesData[Quantity])=0,0,SUMPRODUCT((TEXT(SalesData[Date],"mmm yyyy")=A12)*SalesData[Quantity])),0) -> 0
A13: Oct 2026 | B13: =IFERROR(IF(SUMPRODUCT((TEXT(SalesData[Date],"mmm yyyy")=A13)*SalesData[Total Revenue (INR)])=0,0,SUMPRODUCT((TEXT(SalesData[Date],"mmm yyyy")=A13)*SalesData[Total Revenue (INR)])),0) -> 0 | C13: =IFERROR(IF(SUMPRODUCT((TEXT(SalesData[Date],"mmm yyyy")=A13)*(SalesData[Order ID]<>""))=0,0,SUMPRODUCT((TEXT(SalesData[Date],"mmm yyyy")=A13)*(SalesData[Order ID]<>""))),0) -> 0 | D13: =IFERROR(IF(SUMPRODUCT((TEXT(SalesData[Date],"mmm yyyy")=A13)*SalesData[Quantity])=0,0,SUMPRODUCT((TEXT(SalesData[Date],"mmm yyyy")=A13)*SalesData[Quantity])),0) -> 0
A14: Nov 2026 | B14: =IFERROR(IF(SUMPRODUCT((TEXT(SalesData[Date],"mmm yyyy")=A14)*SalesData[Total Revenue (INR)])=0,0,SUMPRODUCT((TEXT(SalesData[Date],"mmm yyyy")=A14)*SalesData[Total Revenue (INR)])),0) -> 0 | C14: =IFERROR(IF(SUMPRODUCT((TEXT(SalesData[Date],"mmm yyyy")=A14)*(SalesData[Order ID]<>""))=0,0,SUMPRODUCT((TEXT(SalesData[Date],"mmm yyyy")=A14)*(SalesData[Order ID]<>""))),0) -> 0 | D14: =IFERROR(IF(SUMPRODUCT((TEXT(SalesData[Date],"mmm yyyy")=A14)*SalesData[Quantity])=0,0,SUMPRODUCT((TEXT(SalesData[Date],"mmm yyyy")=A14)*SalesData[Quantity])),0) -> 0
A15: Dec 2026 | B15: =IFERROR(IF(SUMPRODUCT((TEXT(SalesData[Date],"mmm yyyy")=A15)*SalesData[Total Revenue (INR)])=0,0,SUMPRODUCT((TEXT(SalesData[Date],"mmm yyyy")=A15)*SalesData[Total Revenue (INR)])),0) -> 0 | C15: =IFERROR(IF(SUMPRODUCT((TEXT(SalesData[Date],"mmm yyyy")=A15)*(SalesData[Order ID]<>""))=0,0,SUMPRODUCT((TEXT(SalesData[Date],"mmm yyyy")=A15)*(SalesData[Order ID]<>""))),0) -> 0 | D15: =IFERROR(IF(SUMPRODUCT((TEXT(SalesData[Date],"mmm yyyy")=A15)*SalesData[Quantity])=0,0,SUMPRODUCT((TEXT(SalesData[Date],"mmm yyyy")=A15)*SalesData[Quantity])),0) -> 0
A20: KPI | B20: Value
A21: Total Revenue (INR) | B21: =SUM(SalesData[Total Revenue (INR)]) -> 420732
A22: Total Orders | B22: =COUNTA(SalesData[Order ID]) -> 200
A23: Total Units Sold | B23: =SUM(SalesData[Quantity]) -> 588
A24: Avg Order Value (INR) | B24: =IFERROR(SUM(SalesData[Total Revenue (INR)])/COUNTA(SalesData[Order ID]),0) -> 2103.66
